advanced_features/__init__.py
advanced_features/blockchain_cryptography_functions.py
advanced_features/cryptographic_audit_log.py
advanced_features/group_e2e_api.py
advanced_features/group_e2e_encryption.py
advanced_features/homomorphic_encryption.py
advanced_features/hybrid_pqc_engine.py
advanced_features/hybrid_pqc_enhanced.py
advanced_features/ibe_cryptography.py
advanced_features/memory_encryption_unit.py
advanced_features/pqc_cryptography.py
advanced_features/secure_enclave_mpc.py
advanced_features/secure_messaging_protocol.py
advanced_features/secure_mpc_enclaves.py
advanced_features/secure_multi_party_computation.py
advanced_features/security_hardening.py
advanced_features/side_channel_protection.py
advanced_features/tamper_resistant_data_structures.py
advanced_features/threshold_multisig.py
advanced_features/threshold_multisig_enhanced.py
advanced_features/white_box_cryptography.py
core_cryptography/__init__.py
core_cryptography/algorithm_agility_versioning.py
core_cryptography/algorithm_manager.py
core_cryptography/asymmetric_encryption.py
core_cryptography/crypto_suite_registry.py
core_cryptography/encryption_framework.py
core_cryptography/enhanced_algorithm_manager.py
core_cryptography/plausible_deniability.py
core_cryptography/symmetric_encryption.py
data_protection/__init__.py
data_protection/compression_unit.py
data_protection/data_obfuscation_unit.py
data_protection/data_protection_manager.py
data_protection/data_type_manager.py
data_protection/secure_memory_handling.py
key_management/__init__.py
key_management/enhanced_kdf.py
key_management/enhanced_kdf_password.py
key_management/enhanced_key_manager.py
key_management/envelope_encryption_kms.py
key_management/key_exchange.py
key_management/key_generator.py
key_management/key_manager.py
key_management/kms_provider.py
key_management/secure_key_store.py
post_quantum_cryptography/__init__.py
post_quantum_cryptography/post_quantum_cryptography_unit.py
specialized_security/__init__.py
zyracrypt-2.0.1.dist-info/licenses/LICENSE
zyracrypt-2.0.1.dist-info/METADATA
zyracrypt-2.0.1.dist-info/WHEEL
zyracrypt-2.0.1.dist-info/top_level.txt
zyracrypt-2.0.1.dist-info/RECORD
