Metadata-Version: 2.4
Name: zyracrypt
Version: 2.0.1
Summary: Enterprise-grade cryptographic library providing advanced encryption, post-quantum cryptography, key management, threshold signatures, and secure enclaves
Author-email: Abdulaziz Alqudimi <eng7mi@gmail.com>
Maintainer-email: Alqudimi Technology <alqudimitechnology@gmail.com>
License: MIT
Project-URL: Homepage, https://github.com/Alqudimi/ZyraCrypt
Project-URL: Documentation, https://github.com/Alqudimi/ZyraCrypt/main/docs
Project-URL: Repository, https://github.com/Alqudimi/ZyraCrypt
Project-URL: Bug Tracker, https://github.com/Alqudimi/ZyraCrypt/issues
Project-URL: Changelog, https://github.com/Alqudimi/ZyraCrypt/releases
Keywords: cryptography,encryption,security,post-quantum,pqc,key-management,threshold-signatures,multi-party-computation,secure-enclaves,homomorphic-encryption,steganography,blockchain-crypto
Classifier: Development Status :: 4 - Beta
Classifier: Intended Audience :: Developers
Classifier: Intended Audience :: Information Technology
Classifier: Intended Audience :: Science/Research
Classifier: Topic :: Security :: Cryptography
Classifier: Topic :: Software Development :: Libraries :: Python Modules
Classifier: Programming Language :: Python :: 3
Classifier: Programming Language :: Python :: 3.8
Classifier: Programming Language :: Python :: 3.9
Classifier: Programming Language :: Python :: 3.10
Classifier: Programming Language :: Python :: 3.11
Classifier: Programming Language :: Python :: 3.12
Classifier: License :: OSI Approved :: MIT License
Classifier: Operating System :: OS Independent
Classifier: Typing :: Typed
Requires-Python: >=3.8
License-File: LICENSE
Requires-Dist: cryptography>=42.0.0
Requires-Dist: pynacl>=1.5.0
Requires-Dist: argon2-cffi>=23.1.0
Requires-Dist: pillow>=10.0.0
Provides-Extra: pqc
Requires-Dist: liboqs-python>=0.10.0; extra == "pqc"
Provides-Extra: api
Requires-Dist: flask>=3.0.0; extra == "api"
Requires-Dist: flask-cors>=4.0.0; extra == "api"
Provides-Extra: database
Requires-Dist: flask-sqlalchemy>=3.0.0; extra == "database"
Requires-Dist: psycopg2-binary>=2.9.0; extra == "database"
Provides-Extra: email
Requires-Dist: email-validator>=2.0.0; extra == "email"
Provides-Extra: dev
Requires-Dist: pytest>=7.4.0; extra == "dev"
Requires-Dist: pytest-cov>=4.1.0; extra == "dev"
Requires-Dist: black>=23.0.0; extra == "dev"
Requires-Dist: ruff>=0.1.0; extra == "dev"
Requires-Dist: mypy>=1.0.0; extra == "dev"
Requires-Dist: build>=1.0.0; extra == "dev"
Requires-Dist: twine>=4.0.0; extra == "dev"
Provides-Extra: docs
Requires-Dist: sphinx>=7.0.0; extra == "docs"
Requires-Dist: sphinx-rtd-theme>=1.3.0; extra == "docs"
Provides-Extra: all
Requires-Dist: liboqs-python>=0.10.0; extra == "all"
Requires-Dist: flask>=3.0.0; extra == "all"
Requires-Dist: flask-cors>=4.0.0; extra == "all"
Requires-Dist: flask-sqlalchemy>=3.0.0; extra == "all"
Requires-Dist: psycopg2-binary>=2.9.0; extra == "all"
Requires-Dist: email-validator>=2.0.0; extra == "all"
Dynamic: license-file
